21_Days_of_RTL/Day4_ALU/Day4_ALU.v
// A simple ALU

module day4 (
  input     logic [7:0]   a_i,
  input     logic [7:0]   b_i,
  input     logic [2:0]   op_i,

  output    logic [7:0]   alu_o
);

  always @ (op_i, a_i, b_i) begin
    case(op_i)
      3'b000: alu_o = a_i + b_i;
      3'b001: alu_o = a_i - b_i;
      3'b010: alu_o = {a_i[4:0], b_i[2:0]};
      3'b011: alu_o = {b_i[2:0], a_i[7:3]};
      3'b100: alu_o = a_i & b_i;
      3'b101: alu_o = a_i | b_i;
      3'b110: alu_o = a_i ^ b_i;
      3'b111: alu_o = {8{(a_i == b_i)}};
    endcase
    end


endmodule

// 3'b000	ADD	-
// 3'b001	SUB	-
// 3'b010	SLL	Vector a should left shift using bits 2:0 of vector b
// 3'b011	LSR	Vector a should right shift using bits 2:0 of vector b
// 3'b100	AND	-
// 3'b101	OR	-
// 3'b110	XOR	-
// 3'b111	EQL	Output should be 1 when equal otherwise 0

21_Days_of_RTL/Day4_ALU/Day4_ALU_TB.v

`timescale 1ns/1ns
`include "Day4_ALU.v"

module day4_tb ();



    logic [7:0]   a_i;
    logic [7:0]   b_i;
    logic [2:0]   op_i;

    logic [7:0]   alu_o;

    day4 DAY4(.*);

    initial begin
        $dumpfile("Day4_ALU_TB.vcd");
        $dumpvars(0, day4_tb);
    end

    initial begin

        for (int i=0; i<10; i++) begin
            a_i = $urandom_range(0, 8'hFF);
            b_i = $urandom_range(0, 8'hFF);
            op_i = $urandom_range(0, 3'b111);
            #5;
        end
        $finish();

    end


    
endmodule

21_Days_of_RTL/Day4_ALU/Day4_ALU_TB.vcd
$date
	Wed Aug 14 20:53:39 2024
$end
$version
	Icarus Verilog
$end
$timescale
	1ns
$end
$scope module day4_tb $end
$var wire 8 ! alu_o [7:0] $end
$var reg 8 " a_i [7:0] $end
$var reg 8 # b_i [7:0] $end
$var reg 3 $ op_i [2:0] $end
$scope module DAY4 $end
$var wire 8 % a_i [7:0] $end
$var wire 8 & b_i [7:0] $end
$var wire 3 ' op_i [2:0] $end
$var reg 8 ( alu_o [7:0] $end
$upscope $end
$scope begin $ivl_for_loop0 $end
$var integer 32 ) i [31:0] $end
$upscope $end
$upscope $end
$enddefinitions $end
$comment Show the parameter values. $end
$dumpall
$end
#0
$dumpvars
b0 )
b11010010 (
b0 '
b1000000 &
b10010010 %
b0 $
b1000000 #
b10010010 "
b11010010 !
$end
#5
b10110111 !
b10110111 (
b110 $
b110 '
b10000110 #
b10000110 &
b110001 "
b110001 %
b1 )
#10
b0 !
b0 (
b100 $
b100 '
b1001 #
b1001 &
b110010 "
b110010 %
b10 )
#15
b10000010 !
b10000010 (
b10111011 #
b10111011 &
b10000110 "
b10000110 %
b11 )
#20
b0 !
b0 (
b111 $
b111 '
b11000110 #
b11000110 &
b11110110 "
b11110110 %
b100 )
#25
b11010 !
b11010 (
b10 $
b10 '
b1100010 #
b1100010 &
b1100011 "
b1100011 %
b101 )
#30
b101101 !
b101101 (
b0 $
b0 '
b111011 #
b111011 &
b11110010 "
b11110010 %
b110 )
#35
b111000 !
b111000 (
b11 $
b11 '
b11111001 #
b11111001 &
b11000111 "
b11000111 %
b111 )
#40
b1110110 !
b1110110 (
b101 $
b101 '
b1100010 #
b1100010 &
b1110100 "
b1110100 %
b1000 )
#45
b1001000 !
b1001000 (
b1 $
b1 '
b10110 #
b10110 &
b1011110 "
b1011110 %
b1001 )
#50
b1010 )
