Day3_Edge_Detect/Day3_Edge_Detect.v
 // An edge detector

module day3 (
  input     wire    clk,
  input     wire    reset,

  input     wire    a_i,

  output    wire    rising_edge_o,
  output    wire    falling_edge_o,
  output    wire    dual_edge_o
);

 logic d_q;
// rising edge detector
 always_ff @ (posedge clk or posedge reset) begin
    if(reset) begin
        d_q <= 1'b0;
    end else begin
        d_q <= a_i;
    end
 end

 assign rising_edge_o = a_i & (!d_q);
 assign falling_edge_o = (!a_i) & d_q;
 assign dual_edge_o = a_i ^ d_q;


//falling edge detector

  
endmodule

Day3_Edge_Detect/Day3_Edge_Detect_TB.v
`timescale 1ns/1ns
`include "Day3_Edge_Detect.v"

module day3_tb ();

    logic clk;
    logic reset;

    logic a_i;

    logic rising_edge_o;
    logic falling_edge_o;
    logic dual_edge_o;

    day3 DAY3(.*);

    initial begin
        $dumpfile("Day3_Edge_Detect_TB.vcd");
        $dumpvars(0, day3_tb);
        $dumpvars(0, DAY3.d_q); // Add internal register d_q to the dump
    end

    always begin
        clk = 1'b0;
        #5;
        clk = 1'b1;
        #5;
    end

    initial begin
        $display("Starting Simulation \n");

        reset = 1'b1;
        a_i = 1'b0;
        @(posedge clk);
        reset = 1'b0;
        // @(posedge clk);
        // a_i = 1'b1;
        // @(posedge clk);
        // @(posedge clk);
        // @(posedge clk);
        // a_i = 1'b0;
        // @(posedge clk);
        // @(posedge clk);
        // a_i = 1'b1;
        // @(posedge clk);
        // @(posedge clk);
        // @(negedge clk);
        // a_i = 1'b0;
        // @(posedge clk);
        // @(posedge clk);

        #7;
        a_i = 1'b1;
        #10;
        a_i = 1'b0;
        #10;
        a_i = 1'b1;
        #10;
        a_i = 1'b0;
        #3;


        $display("Simulation Complete");
        $finish();

    end
endmodule

Day3_Edge_Detect/Day3_Edge_Detect_TB.vcd
$date
	Wed Nov 27 22:49:42 2024
$end
$version
	Icarus Verilog
$end
$timescale
	1ns
$end
$scope module day3_tb $end
$var wire 1 ! rising_edge_o $end
$var wire 1 " falling_edge_o $end
$var wire 1 # dual_edge_o $end
$var reg 1 $ a_i $end
$var reg 1 % clk $end
$var reg 1 & reset $end
$scope module DAY3 $end
$var wire 1 $ a_i $end
$var wire 1 % clk $end
$var wire 1 # dual_edge_o $end
$var wire 1 " falling_edge_o $end
$var wire 1 & reset $end
$var wire 1 ! rising_edge_o $end
$var reg 1 ' d_q $end
$upscope $end
$upscope $end
$enddefinitions $end
$comment Show the parameter values. $end
$dumpall
$end
#0
$dumpvars
0'
1&
0%
0$
0#
0"
0!
$end
#5
0&
1%
#10
0%
#12
1!
1#
1$
#15
0!
0#
1'
1%
#20
0%
#22
1#
1"
0$
#25
0#
0"
0'
1%
#30
0%
#32
1!
1#
1$
#35
0!
0#
1'
1%
#40
0%
#42
1#
1"
0$
#45
0#
0"
0'
1%
