Day1_MUX/Day1_MUX.v
// A simple mux

module Day1_Mux(
  input   wire [7:0]    a_i,
  input   wire [7:0]    b_i,
  input   wire          sel_i,
  output  wire [7:0]    y_o
);

  // Write your logic here...
  assign y_o = (sel_i == 1'b0) ? a_i : b_i;

endmodule

21_Days_of_RTL/Day1_MUX/Day1_MUX_TB.v
// A simple TB for mux
`timescale 1ns/1ns
`include "Day1_Mux.v"

module Day1_MUX_TB ();

  logic [7:0] a_i;
  logic [7:0] b_i;
  logic       sel_i;
  logic [7:0] y_o;

  Day1_Mux DAY1 (.*);
  
  
  initial begin
    $dumpfile("Day1_MUX_TB.vcd");
    $dumpvars(0, Day1_MUX_TB);

  end

  initial begin
    for (int i = 0; i < 10; i++) begin
      a_i   = $urandom_range (0, 8'hFF);
      b_i   = $urandom_range (0, 8'hFF);
      sel_i = $random%2;
      #5;
    end
    $finish();
  end

endmodule

Day1_MUX/Day1_MUX_TB.vcd
$date
	Wed Nov 27 22:13:16 2024
$end
$version
	Icarus Verilog
$end
$timescale
	1ns
$end
$scope module Day1_MUX_TB $end
$var wire 8 ! y_o [7:0] $end
$var reg 8 " a_i [7:0] $end
$var reg 8 # b_i [7:0] $end
$var reg 1 $ sel_i $end
$scope module DAY1 $end
$var wire 8 % a_i [7:0] $end
$var wire 8 & b_i [7:0] $end
$var wire 1 $ sel_i $end
$var wire 8 ' y_o [7:0] $end
$upscope $end
$scope begin $ivl_for_loop0 $end
$var integer 32 ( i [31:0] $end
$upscope $end
$upscope $end
$enddefinitions $end
$comment Show the parameter values. $end
$dumpall
$end
#0
$dumpvars
b0 (
b10010010 '
b1000000 &
b10010010 %
0$
b1000000 #
b10010010 "
b10010010 !
$end
#5
b110001 !
b110001 '
1$
b110001 #
b110001 &
b100 "
b100 %
b1 (
#10
b11000110 !
b11000110 '
b11000110 #
b11000110 &
b10000110 "
b10000110 %
b10 (
#15
b1001 !
b1001 '
b1001 #
b1001 &
b110010 "
b110010 %
b11 (
#20
b10000110 !
b10000110 '
b10000110 #
b10000110 &
b10000000 "
b10000000 %
b100 (
#25
b10011110 !
b10011110 '
b10011110 #
b10011110 &
b10111011 "
b10111011 %
b101 (
#30
b11000110 !
b11000110 '
b11000110 #
b11000110 &
b11110110 "
b11110110 %
b110 (
#35
b11111100 !
b11111100 '
0$
b1100011 #
b1100011 &
b11111100 "
b11111100 %
b111 (
#40
b1010101 !
b1010101 '
1$
b1010101 #
b1010101 &
b1100010 "
b1100010 %
b1000 (
#45
b111011 !
b111011 '
b111011 #
b111011 &
b11110010 "
b11110010 %
b1001 (
#50
b1010 (
